h2osteam/__init__.py
h2osteam/deprecated.py
h2osteam/h2osteam.py
h2osteam/backend/__init__.py
h2osteam/backend/api.py
h2osteam/backend/connection.py
h2osteam/clients/__init__.py
h2osteam/clients/admin/__init__.py
h2osteam/clients/admin/admin_client.py
h2osteam/clients/driverless/__init__.py
h2osteam/clients/driverless/driverless_client.py
h2osteam/clients/driverless/driverless_instance.py
h2osteam/clients/driverless/multinode_client.py
h2osteam/clients/h2o/__init__.py
h2osteam/clients/h2o/h2o_client.py
h2osteam/clients/h2o/h2o_cluster.py
h2osteam/clients/h2ok8s/__init__.py
h2osteam/clients/h2ok8s/h2ok8s.py
h2osteam/clients/k8sadmin/__init__.py
h2osteam/clients/k8sadmin/admin_client.py
h2osteam/clients/sparkling/__init__.py
h2osteam/clients/sparkling/sparkling_client.py
h2osteam/clients/sparkling/sparkling_cluster.py
h2osteam/typed_backend/__init__.py
h2osteam/typed_backend/typed_api.py
h2osteam/typed_backend/typed_connection.py
h2osteam/typed_clients/__init__.py
h2osteam/typed_clients/admink8s/__init__.py
h2osteam/typed_clients/admink8s/admin_kubernetes_client.py
h2osteam/utils/__init__.py
h2osteam/utils/cluster_sizing.py
h2osteam/utils/dai_connect.py
h2osteam/utils/progress.py
h2osteam/utils/utils.py
tests/__init__.py
tests/cloudera/__init__.py
tests/cloudera/tests.py
tests/hadoop/__init__.py
tests/hadoop/conftest.py
tests/hadoop/helper.py
tests/hadoop/test_cluster_save.py
tests/hadoop/test_connection.py
tests/hadoop/test_h2o_client.py
tests/hadoop/test_print_env_and_profile.py
tests/hadoop/test_sparkling_client.py
h2osteam-1.9.16.dist-info/METADATA
h2osteam-1.9.16.dist-info/WHEEL
h2osteam-1.9.16.dist-info/top_level.txt
h2osteam-1.9.16.dist-info/RECORD
