Metadata-Version: 2.1
Name: h2osteam
Version: 1.9.16
Summary: Python client for H2O Enterprise Steam
Home-page: https://github.com/h2oai/h2o-secure
Author: H2O.ai
Author-email: support@h2o.ai
License: Apache v2
Platform: UNKNOWN
Classifier: Development Status :: 5 - Production/Stable
Classifier: Topic :: Scientific/Engineering :: Artificial Intelligence
Classifier: License :: OSI Approved :: Apache Software License
Classifier: Programming Language :: Python :: 2
Classifier: Programming Language :: Python :: 2.7
Classifier: Programming Language :: Python :: 3
Classifier: Programming Language :: Python :: 3.5
Classifier: Programming Language :: Python :: 3.6
Classifier: Programming Language :: Python :: 3.7
Classifier: Programming Language :: Python :: 3.8
Requires-Python: >=2.7, !=3.0.*, !=3.1.*, !=3.2.*, !=3.3.*, !=3.4.*, <4
Requires-Dist: looseversion
Requires-Dist: requests
Requires-Dist: requests-toolbelt
Requires-Dist: tabulate
Requires-Dist: future
Requires-Dist: colorama>=0.3.8
Requires-Dist: toml
